skymavis_captcha_bypass/__init__.py
skymavis_captcha_bypass/captcha.py
skymavis_captcha_bypass/vision.py
skymavis_captcha_bypass-1.1.dist-info/METADATA
skymavis_captcha_bypass-1.1.dist-info/WHEEL
skymavis_captcha_bypass-1.1.dist-info/top_level.txt
skymavis_captcha_bypass-1.1.dist-info/RECORD
